{
  "generator-jhipster": {
    "applicationIndex": 1,
    "applicationType": "microservice",
    "authenticationType": "jwt",
    "baseName": "billing",
    "blueprints": [],
    "buildTool": "gradle",
    "cacheProvider": "hazelcast",
    "clientFramework": "no",
    "clientPackageManager": "npm",
    "creationTimestamp": 1670183563644,
    "databaseType": "sql",
    "devDatabaseType": "mysql",
    "dtoSuffix": "DTO",
    "enableGradleEnterprise": false,
    "enableHibernateCache": true,
    "enableSwaggerCodegen": false,
    "enableTranslation": true,
    "entities": ["Price"],
    "entitySuffix": "",
    "gradleEnterpriseHost": "",
    "jhiPrefix": "jhi",
    "jhipsterVersion": "7.9.3",
    "jwtSecretKey": "ODY2ZDQxNGMyYzk2ZDE3NzI3OTZkMjkwN2ExNmM2YTRlZDM3N2U0NzZiYjFlZmI1YzI3MTJhZjlkMWE5NzViY2EwNzk0NThmNDUwZjc5YzVjMTRmOTRkNmIyY2VhOWVjYWU1NDNjZDNmZDcxZjQ5YzU0ZjY2MzM4NzIwZWEyMmM=",
    "languages": ["en"],
    "lastLiquibaseTimestamp": 1670183623000,
    "messageBroker": false,
    "microfrontend": false,
    "monorepository": true,
    "nativeLanguage": "en",
    "otherModules": [],
    "packageFolder": "com/billing",
    "packageName": "com.billing",
    "pages": [],
    "prodDatabaseType": "mysql",
    "reactive": false,
    "searchEngine": false,
    "serverPort": "8081",
    "serviceDiscoveryType": "eureka",
    "skipCheckLengthOfIdentifier": false,
    "skipClient": true,
    "skipCommitHook": true,
    "skipFakeData": false,
    "skipUserManagement": true,
    "testFrameworks": [],
    "websocket": false,
    "withAdminUi": false
  }
}
